warpzone/__init__.py
warpzone/blobstorage/__init__.py
warpzone/blobstorage/client.py
warpzone/db/__init__.py
warpzone/db/client.py
warpzone/deltastorage/__init__.py
warpzone/deltastorage/data_types.py
warpzone/deltastorage/generated_columns.py
warpzone/deltastorage/lock_client.py
warpzone/deltastorage/schema.py
warpzone/deltastorage/slicing.py
warpzone/deltastorage/store.py
warpzone/deltastorage/table.py
warpzone/enums/__init__.py
warpzone/enums/topicenum.py
warpzone/function/__init__.py
warpzone/function/checks.py
warpzone/function/functionize.py
warpzone/function/integrations.py
warpzone/function/monitor.py
warpzone/function/process.py
warpzone/function/processors/__init__.py
warpzone/function/processors/dependencies.py
warpzone/function/processors/outputs.py
warpzone/function/processors/triggers.py
warpzone/function/signature.py
warpzone/function/types.py
warpzone/healthchecks/__init__.py
warpzone/healthchecks/model.py
warpzone/monitor/__init__.py
warpzone/monitor/logs.py
warpzone/monitor/traces.py
warpzone/servicebus/data/__init__.py
warpzone/servicebus/data/client.py
warpzone/servicebus/events/__init__.py
warpzone/servicebus/events/client.py
warpzone/servicebus/events/triggers.py
warpzone/tablestorage/db/__init__.py
warpzone/tablestorage/db/base_client.py
warpzone/tablestorage/db/client.py
warpzone/tablestorage/db/table_config.py
warpzone/tablestorage/tables/__init__.py
warpzone/tablestorage/tables/client.py
warpzone/tablestorage/tables/entities.py
warpzone/tablestorage/tables/helpers.py
warpzone/testing/__init__.py
warpzone/testing/assertions.py
warpzone/testing/data.py
warpzone/testing/matchers.py
warpzone/tools/__init__.py
warpzone/tools/copy.py
warpzone/transform/__init__.py
warpzone/transform/data.py
warpzone/transform/schema.py
warpzone_sdk-15.1.0.dist-info/METADATA
warpzone_sdk-15.1.0.dist-info/WHEEL
warpzone_sdk-15.1.0.dist-info/RECORD
