Metadata-Version: 2.4
Name: warpzone-sdk
Version: 15.1.0
Summary: The main objective of this package is to centralize logic used to interact with Azure Functions, Azure Service Bus and Azure Table Storage
Author: Team Enigma
Author-email: enigma@energinet.dk
Requires-Python: >=3.10
Classifier: Programming Language :: Python :: 3
Classifier: Programming Language :: Python :: 3.10
Classifier: Programming Language :: Python :: 3.11
Classifier: Programming Language :: Python :: 3.12
Classifier: Programming Language :: Python :: 3.13
Classifier: Programming Language :: Python :: 3.14
Requires-Dist: aiohttp (>=3.8.3)
Requires-Dist: azure-core (>=1.26.3)
Requires-Dist: azure-data-tables (>=12.4.0)
Requires-Dist: azure-functions (>=1.12.0)
Requires-Dist: azure-identity (>=1.15.0)
Requires-Dist: azure-monitor-opentelemetry-exporter (>=1.0.0b36)
Requires-Dist: azure-servicebus (>=7.8.0)
Requires-Dist: azure-storage-blob (>=12.14.1)
Requires-Dist: cryptography (==43.0.3)
Requires-Dist: datamazing (>=5.1.6)
Requires-Dist: deltalake (==1.2.1)
Requires-Dist: numpy (>=1.26.4)
Requires-Dist: obstore (>=0.8.2)
Requires-Dist: opentelemetry-sdk (>=1.32.0)
Requires-Dist: pandas (>=2.0.3)
Requires-Dist: polars (>=1.33.1)
Requires-Dist: pyarrow (>=19.0.0)
Requires-Dist: typeguard (>=4.0.1)
